{"category":{"name":"Foundation Model","normalized_name":"foundation-model","subcategories":[{"name":"Code","normalized_name":"code"}]},"items":[{"category":"Foundation Model","id":"foundation-model--code--tabby","name":"Tabby","logo":"logos/c2216bfb8850433e30398dfc7e063c26ebbb9393c39f42dd802d05047eace911.svg","subcategory":"Code","maturity":"opensource","oss":true},{"category":"Foundation Model","id":"foundation-model--code--tabnine","name":"Tabnine","logo":"logos/3ab4f05b22d3203ef8772f1325c7e9a91eb5129a09726ebaefbb4987701952d0.svg","subcategory":"Code"}]}